Malayalam_News_Scraper/__init__.py
Malayalam_News_Scraper/main.py
Malayalam_News_Scraper-1.0.0.dist-info/LICENSE
Malayalam_News_Scraper-1.0.0.dist-info/METADATA
Malayalam_News_Scraper-1.0.0.dist-info/WHEEL
Malayalam_News_Scraper-1.0.0.dist-info/top_level.txt
Malayalam_News_Scraper-1.0.0.dist-info/RECORD
