Metadata-Version: 2.1
Name: Malayalam_News_Scraper
Version: 1.0.0
License-File: LICENSE
